{
  "timeZone": "America/Los_Angeles",
  "dependencies": {
    "libraries": [{
      "userSymbol": "OAuth2",
      "libraryId": "1B7FSrk5Zi6L1rSxxTDgDEUsPzlukDsi4KGuTMorsTQHhGBzBkMun4iDF",
      "version": "40"
    }]
  },
  "oauthScopes": ["https://www.googleapis.com/auth/script.external_request", "https://www.googleapis.com/auth/userinfo.email"],
  "runtimeVersion": "V8",
  "urlFetchWhitelist": ["https://redivis.com/api","https://accounts.google.com/o/oauth2", "https://redivis.com/oauth"],
  "dataStudio": {
    "name": "Redivis",
    "logoUrl": "https://storage.googleapis.com/redivis-public/icon-square-40px.png",
    "company": "Redivis",
    "companyUrl": "https://redivis.com",
    "addonUrl": "https://docs.redivis.com/reference/export-and-integrations/data-studio",
    "supportUrl": "https://github.com/redivis/meta/issues/new/choose",
    "description": "Create interactive visualizations with data hosted on Redivis. Redivis allows organizations to distribute data to the research community, while providing researchers with the tools to discover, understand, and analyze data within a collaborative and open ecosystem.",
    "sources": ["REDIVIS"],
    "shortDescription": "Create interactive visualizations with data stored on Redivis.",
    "privacyPolicyUrl": "https://redivis.com/privacy",
    "termsOfServiceUrl": "https://redivis.com/terms",
    "authType": ["OAUTH2"],
    "feeType": ["FREE"],
    "templates": {
      "default": "16d9578c-67d3-45de-9105-f628f80d0655"
    },
    "advancedServices": {
      "schema": true,
      "data": true
    },
    "forceViewersCredentials": false
  }
}